babbab/__init__.py
babbab/core.py
babbab/stats.py
babbab/viz.py
babbab-0.3.3.dist-info/LICENSE
babbab-0.3.3.dist-info/WHEEL
babbab-0.3.3.dist-info/METADATA
babbab-0.3.3.dist-info/RECORD
