Metadata-Version: 2.1
Name: babbab
Version: 0.3.3
Summary: BAyesian Beta-Binomial AB testing (BABBAB), is an implementation
Author-email: Juan González-Vallinas <juan@multilayer.io>
Classifier: License :: OSI Approved :: MIT License
Requires-Dist: matplotlib>=3.5.2
Requires-Dist: pymc>=4.1.2
Requires-Dist: arviz>=0.12.1
Requires-Dist: pytest>=6.2.5 ; extra == "test"
Requires-Dist: jupyter>=1.0.0 ; extra == "test"
Requires-Dist: jupyterlab>=3.1.14 ; extra == "test"
Requires-Dist: black>=21.9b0 ; extra == "test"
Requires-Dist: flake8>=3.9.2 ; extra == "test"
Requires-Dist: isort>=5.9.3 ; extra == "test"
Project-URL: Home, https://github.com/multilayer-io/babbab
Provides-Extra: test
